scproxymesh/__init__.py
scrapy_proxymesh_py3-0.0.5.dist-info/LICENSE
scrapy_proxymesh_py3-0.0.5.dist-info/WHEEL
scrapy_proxymesh_py3-0.0.5.dist-info/METADATA
scrapy_proxymesh_py3-0.0.5.dist-info/RECORD
